halp/directed_hypergraph.py
halp/directed_hypergraph.pyc
halp/undirected_hypergraph.py
halp/undirected_hypergraph.pyc
halp/__init__.py
halp/__init__.pyc
halp/algorithms/directed_paths.py
halp/algorithms/directed_random_walk.py
halp/algorithms/k_shortest_hyperpaths.py
halp/algorithms/undirected_partitioning.py
halp/algorithms/__init__.py
halp/utilities/directed_graph_transformations.py
halp/utilities/directed_matrices.py
halp/utilities/directed_statistics.py
halp/utilities/priority_queue.py
halp/utilities/undirected_graph_transformations.py
halp/utilities/undirected_matrices.py
halp/utilities/__init__.py
halp-1.0.0.dist-info/DESCRIPTION.rst
halp-1.0.0.dist-info/METADATA
halp-1.0.0.dist-info/metadata.json
halp-1.0.0.dist-info/RECORD
halp-1.0.0.dist-info/top_level.txt
halp-1.0.0.dist-info/WHEEL
tests/test_directed_hypergraph.py
tests/test_undirected_hypergraph.py
tests/__init__.py
tests/__init__.pyc
tests/__pycache__/test_directed_hypergraph.cpython-27-PYTEST.pyc
tests/__pycache__/test_undirected_hypergraph.cpython-27-PYTEST.pyc
